fortitude/README.md
fortitude/__init__.py
fortitude/backend/endpoints/__init__.py
fortitude/backend/mcp/__init__.py
fortitude/backend/mcp/client.py
fortitude/backend/mcp/sampling.py
fortitude/backend/mcp/scaffolds.py
fortitude/backend/mcp/server.py
fortitude/backend/models/__init__.py
fortitude/backend/models/example.py
fortitude/backend/registry.py
fortitude/backend/server.py
fortitude/cli/__init__.py
fortitude/cli/advanced_scaffolding.py
fortitude/cli/commands.py
fortitude/cli/fort.py
fortitude/cli/mcp_commands.py
fortitude/cli/model_generator.py
fortitude/cli/model_mcp_commands.py
fortitude/cli/scaffolding.py
fortitude/core/__init__.py
fortitude/core/visualization.py
fortitude/fortitude/__init__.py
fortitude/fortitude/backend/endpoints/__init__.py
fortitude/fortitude/backend/mcp/__init__.py
fortitude/fortitude/backend/mcp/client.py
fortitude/fortitude/backend/mcp/sampling.py
fortitude/fortitude/backend/mcp/scaffolds.py
fortitude/fortitude/backend/mcp/server.py
fortitude/fortitude/backend/models/__init__.py
fortitude/fortitude/backend/models/example.py
fortitude/fortitude/backend/registry.py
fortitude/fortitude/backend/server.py
fortitude/fortitude/cli/__init__.py
fortitude/fortitude/cli/advanced_scaffolding.py
fortitude/fortitude/cli/commands.py
fortitude/fortitude/cli/fort.py
fortitude/fortitude/cli/mcp_commands.py
fortitude/fortitude/cli/model_generator.py
fortitude/fortitude/cli/model_mcp_commands.py
fortitude/fortitude/cli/scaffolding.py
fortitude/fortitude/core/__init__.py
fortitude/poetry.lock
fortitude/pyproject.toml
fortitude/ui/app/[model]/page.tsx
fortitude/ui/app/analyze/[model]/[id]/page.tsx
fortitude/ui/app/api/models/route.ts
fortitude/ui/app/api/sample/route.ts
fortitude/ui/app/layout.tsx
fortitude/ui/app/mcp/page.tsx
fortitude/ui/app/new/[model]/page.tsx
fortitude/ui/app/page.tsx
fortitude/ui/components/LLMSampler.tsx
fortitude/ui/components/ModelForm.tsx
fortitude/ui/components/ModelViewer.tsx
fortitude/ui/components/Navigation.tsx
fortitude_framework-0.1.0.dist-info/METADATA
fortitude_framework-0.1.0.dist-info/WHEEL
fortitude_framework-0.1.0.dist-info/entry_points.txt
fortitude_framework-0.1.0.dist-info/RECORD
