Metadata-Version: 2.3
Name: fortitude-framework
Version: 0.1.0
Summary: A web framework with server-side components defined as Pydantic models
Keywords: web,framework,pydantic,nextjs,fastapi
Author: Your Name
Author-email: your.email@example.com
Requires-Python: >=3.9
Classifier: Development Status :: 3 - Alpha
Classifier: Intended Audience :: Developers
Classifier: Programming Language :: Python :: 3
Classifier: Programming Language :: Python :: 3.9
Classifier: Programming Language :: Python :: 3.10
Classifier: Programming Language :: Python :: 3.11
Classifier: Programming Language :: Python :: 3.12
Classifier: Programming Language :: Python :: 3.13
Requires-Dist: aiohttp (>=3.8.5)
Requires-Dist: asyncio (>=3.4.3)
Requires-Dist: fastapi (>=0.103.1)
Requires-Dist: pydantic (>=2.4.2)
Requires-Dist: uvicorn (>=0.23.2)
Project-URL: Repository, https://github.com/your-username/fortitude
